colcon_library_path/__init__.py
colcon_library_path/environment/__init__.py
colcon_library_path/environment/library_path.py
colcon_library_path-0.2.0.dist-info/DESCRIPTION.rst
colcon_library_path-0.2.0.dist-info/METADATA
colcon_library_path-0.2.0.dist-info/RECORD
colcon_library_path-0.2.0.dist-info/WHEEL
colcon_library_path-0.2.0.dist-info/entry_points.txt
colcon_library_path-0.2.0.dist-info/metadata.json
colcon_library_path-0.2.0.dist-info/top_level.txt
colcon_library_path-0.2.0.dist-info/zip-safe
